{
  "allItems": [
    12650
  ],
  "equipLocationNames": [
    "Right Hand"
  ],
  "equipLocation": [
    "special_r"
  ],
  "isPackage": false,
  "itemID": 12650,
  "name": "NPC Sentinel Scout Sword",
  "displayName": "",
  "description": "NPC Sentinel Scout Sword",
  "isWeapon": true,
  "internalNotes": null,
  "abilityNames": [],
  "skillIDs": [
    970
  ],
  "behaviorIDs": [
    20237
  ],
  "meleeDamageInfo": {
    "damageCombo": "2+3",
    "chargeUpDamage": "2",
    "doubleJumpSmash": "1",
    "singleJumpSmash": "2"
  },
  "abilityName": "Great Attack with Block",
  "chargeUpDescription": "Blocks 3 attacks while charged",
  "projectileDamageInfo": {
    "chargeUpDamage": "2",
    "projectileDamageCombo": "",
    "isChargeUp": true,
    "chargeUpIsProjectile": false,
    "isProjectileWeapon": false
  },
  "iconURL": "https://xiphoseer.github.io/lu-res/textures/ui/inventory/hands/m2530_26.png",
  "stackSize": 1,
  "price": 0,
  "commendationCost": null,
  "factionTokens": null,
  "levelRequirement": 0
}