{"allItems":[15935,14490],"equipLocationNames":["Headgear","Neck/Back"],"equipLocation":["hair","clavicle"],"itemID":15935,"name":"Apothecary's Hood","displayName":"Apothecary's Hood","description":null,"isWeapon":false,"internalNotes":"heals caster for 3 Life. 4 AP 5 IP","abilityNames":["Armor Boost 4","Imagination Boost 5","Ninja Healing","[DNL] Equipped 1 HOOD Nj SJ Item"],"skillIDs":[363,373,1461,1537],"behaviorIDs":[4245,4255,36235,37628],"Armor":4,"Imagination":5,"cooldowngroup":5,"cooldownTime":10,"projectileDamageInfo":{"projectileDamageCombo":"","isChargeUp":false,"chargeUpIsProjectile":false,"isProjectileWeapon":false},"iconURL":"https://xiphoseer.github.io/lu-res/textures/ui/inventory/hats/m30177_24.png","stackSize":1,"price":11425,"commendationCost":null,"factionTokens":null,"levelRequirement":"15"}