{
  "allItems": [
    16012
  ],
  "equipLocationNames": [
    "Right Hand"
  ],
  "equipLocation": [
    "special_r"
  ],
  "isPackage": false,
  "itemID": 16012,
  "name": "Frakjaw's Maelstrom Battle Mace",
  "displayName": "Frakjaw's Maelstrom Battle Mace",
  "description": "The Skeletons forged this from pure Maelstrom!",
  "isWeapon": true,
  "internalNotes": "for Nya Mission",
  "abilityNames": [],
  "skillIDs": [
    1497,
    1499
  ],
  "behaviorIDs": [
    36888,
    36993
  ],
  "meleeDamageInfo": {
    "damageCombo": "3+7+3+8+3+9",
    "doubleJumpSmash": "5",
    "singleJumpSmash": "7"
  },
  "abilityName": "Ninjago Attack",
  "abilityImaginationCost": 0,
  "cooldowngroup": -1,
  "cooldownTime": -1,
  "localeDescription": "Smashes enemies",
  "projectileDamageInfo": {
    "projectileDamageCombo": "",
    "isChargeUp": false,
    "chargeUpIsProjectile": false,
    "isProjectileWeapon": false
  },
  "iconURL": "https://xiphoseer.github.io/lu-res/textures/ng_ninjago/ui/inventory/hands/maelstrommac.png",
  "stackSize": 1,
  "price": 0,
  "commendationCost": null,
  "factionTokens": null,
  "levelRequirement": "15"
}