{"allItems":[14564],"equipLocationNames":["Left Hand"],"equipLocation":["special_l"],"itemID":14564,"name":"Hatchling Cat's Fish - Orange","displayName":"Orange Cat's Fish","description":"","isWeapon":false,"internalNotes":"Marketing Reward 1 AP 1 IP","abilityNames":[],"skillIDs":[360,369,1401],"behaviorIDs":[4241,4251,32846],"abilityName":"Summon Orange Cat","Armor":1,"Imagination":1,"cooldowngroup":15,"cooldownTime":90,"projectileDamageInfo":{"projectileDamageCombo":"","isChargeUp":false,"chargeUpIsProjectile":false,"isProjectileWeapon":false},"iconURL":"https://xiphoseer.github.io/lu-res/textures/freetrial/ui/inventory/icons/cat-fish.png","stackSize":1,"price":4250,"commendationCost":null,"factionTokens":null,"levelRequirement":0}