{"allItems":[10874],"equipLocationNames":["Extra_1"],"equipLocation":["Extra_1"],"itemID":10874,"name":"LUP Model Reward SpaceCrane","displayName":"Space Crane Model","description":"A model for your property!","isWeapon":false,"internalNotes":null,"abilityNames":[],"skillIDs":[],"behaviorIDs":[],"projectileDamageInfo":{},"iconURL":"https://xiphoseer.github.io/lu-res/textures/ui/inventory/models/lup_ld_spacecrane.png","stackSize":10,"price":1610,"commendationCost":null,"factionTokens":null,"levelRequirement":0}