{
  "allItems": [
    10997
  ],
  "equipLocationNames": [
    null
  ],
  "equipLocation": [
    null
  ],
  "isPackage": false,
  "itemID": 10997,
  "name": "Touch Sensitive Platform Behavior",
  "displayName": "Touch Sensitive Platform Behavior",
  "description": "Model moves up and down when touched.  The model also gives instructions when approached.",
  "isWeapon": false,
  "internalNotes": "TIER 2 Behavior",
  "abilityNames": [],
  "skillIDs": [],
  "behaviorIDs": [],
  "projectileDamageInfo": {},
  "iconURL": "https://xiphoseer.github.io/lu-res/textures/ui/missions/req_shooting_gallery.png",
  "stackSize": 0,
  "price": 0,
  "commendationCost": null,
  "factionTokens": null,
  "levelRequirement": 0
}