{"id":1448,"rewards":[{"name":"FV Gem Surprise Pack","itemID":13113,"count":1},{"name":"FV Gem Surprise Pack","itemID":13102,"count":1}],"type":"Mission","title":"I Have the Power!","giverID":12261,"giverName":"Duke Exeter - Sentinel Faction Leader","returnToID":12261,"returnToName":"Duke Exeter - Sentinel Faction Leader","description":"Blast those Maelstrom invaders back into bricks!","objective":"Find 5 blue X-marks on Crux Prime and then use Duke's sword to call down Imagination Blasts.","chooseOne":1,"stats":[],"LEGOScore":310,"rewardCoins":0,"isRepeatable":0,"vaultSpace":0,"iconurl":"https://xiphoseer.github.io/lu-res/textures/nexustower/ui/missioncomics/nexustower/task_icons/mission_imagination_strike.png"}