{"id":873,"rewards":[],"type":"Mission","title":"Clear Chantey Shanty!","giverID":10300,"giverName":"Sunny Rayhawk - Property Guard","returnToID":10300,"returnToName":"Sunny Rayhawk - Property Guard","description":"There's got to be a way to free that Imagination!","objective":"Find a way to reach the Imagination Orb and clear the Property.","chooseOne":0,"stats":[],"LEGOScore":110,"rewardCoins":150,"isRepeatable":0,"vaultSpace":0,"iconurl":"https://xiphoseer.github.io/lu-res/textures/ui/missioncomics/wonderland/nimbus_station/hud_icons/mission_872.png"}