{"id":874,"rewards":[],"type":"Mission","title":"Clear Raven Bluff!","giverID":10301,"giverName":"Knuck Brassels - Property Guard","returnToID":10301,"returnToName":"Knuck Brassels - Property Guard","description":"I'll stay up and here and watch, if you don't mind.","objective":"Find a way to reach the Imagination Orb and clear the Property.","chooseOne":0,"stats":[],"LEGOScore":210,"rewardCoins":200,"isRepeatable":0,"vaultSpace":0,"iconurl":"https://xiphoseer.github.io/lu-res/textures/ui/missioncomics/wonderland/nimbus_station/hud_icons/mission_872.png"}