{"id":973,"rewards":[{"name":"Faction Token Bag - 5 tokens","itemID":10095,"count":1}],"type":"Mission","title":"Skeleton Tech","giverID":11998,"giverName":"Neido - Ninja of Imagination","returnToID":11998,"returnToName":"Neido - Ninja of Imagination","description":"Strike at the Watchtowers' weak spots. Then smash the Watchmen and retrieve those schematic pages!","objective":"Topple Skeleton Watchtowers, smash the Skeleton Watchmen that fall out, then collect 6 schematic pages.","chooseOne":0,"stats":[],"LEGOScore":305,"rewardCoins":0,"isRepeatable":0,"vaultSpace":0,"iconurl":"https://xiphoseer.github.io/lu-res/textures/ui/missioncomics/wonderland/gnarled_forest/hud_icons/map_blueprint.png"}