{"allItems":[6848],"equipLocationNames":["Right Hand"],"equipLocation":["special_r"],"itemID":6848,"name":"Captain Jack's Volleygun","displayName":"Captain Jack's Volleygun","description":"Requires Imagination to fire.","isWeapon":true,"internalNotes":"3/3/3 Ranged + PBAoE","skillIDs":[872],"behaviorIDs":[16888],"abilityName":"Elite Ranged Attack","abilityImaginationCost":0,"weaponTreeInfo":{"damageCombo":"1+1+1","projectileDamageCombo":"3+3+3","doubleJumpSmash":"2","singleJumpSmash":"3","isChargeUp":true,"chargeUpDamage":"1","chargeUpIsProjectile":false,"isProjectileWeapon":true},"iconURL":"https://xiphoseer.github.io/lu-res/textures/ui/inventory/hands/m2561_131.png","stackSize":1,"price":15000,"commendationCost":83,"factionTokens":null,"levelRequirement":"27"}