{"allItems":[12288],"equipLocationNames":[""],"equipLocation":[""],"itemID":12288,"name":"Snowball","displayName":"Snowball","description":"Double-click to use!","isWeapon":false,"internalNotes":null,"abilityNames":[],"skillIDs":[942],"behaviorIDs":[19636],"abilityName":"Throw Snowball","cooldowngroup":13,"cooldownTime":8,"projectileDamageInfo":{"projectileDamageCombo":"","isChargeUp":false,"chargeUpIsProjectile":false,"isProjectileWeapon":false},"iconURL":"https://xiphoseer.github.io/lu-res/textures/ui/inventory/consumables/snowball.png","stackSize":100,"price":1,"commendationCost":null,"factionTokens":2,"levelRequirement":0}