{"allItems":[12308],"equipLocationNames":["Headgear"],"equipLocation":["hair"],"itemID":12308,"name":"Banneret's Helm","displayName":"Banneret's Helm","description":"","isWeapon":false,"internalNotes":"2 AP 3 IP + Stun","abilityNames":[],"skillIDs":[298,361,371],"behaviorIDs":[17564,4243,4253],"abilityName":"Imagination Boost 3","cooldowngroup":3,"cooldownTime":8,"Armor":2,"Imagination":3,"projectileDamageInfo":{"projectileDamageCombo":"","isChargeUp":false,"chargeUpIsProjectile":false,"isProjectileWeapon":false},"iconURL":"https://xiphoseer.github.io/lu-res/textures/ui/inventory/hats/squireshelm.png","stackSize":1,"price":4450,"commendationCost":null,"factionTokens":null,"levelRequirement":"15"}