{"allItems":[12451],"equipLocationNames":[""],"equipLocation":[""],"itemID":12451,"name":"Thumpin' Bass","displayName":"Thumpin' Bass","description":"Double-click to use!","isWeapon":false,"internalNotes":"Like Portable Drumset. Stat restoration","abilityNames":[],"skillIDs":[975],"behaviorIDs":[20402],"abilityName":"Bass Riff","cooldowngroup":13,"cooldownTime":60,"projectileDamageInfo":{"projectileDamageCombo":"","isChargeUp":false,"chargeUpIsProjectile":false,"isProjectileWeapon":false},"iconURL":"https://xiphoseer.github.io/lu-res/textures/auramar/ui/inventory/misc/qb_bass-guitar.png","stackSize":1,"price":1860,"commendationCost":10,"factionTokens":null,"levelRequirement":0}