{
  "allItems": [
    12479
  ],
  "equipLocationNames": [
    ""
  ],
  "equipLocation": [
    ""
  ],
  "isPackage": false,
  "itemID": 12479,
  "name": "NT Brick Sample A",
  "displayName": "Alien Pod",
  "description": "Return this to Vanda Darkflame.",
  "isWeapon": false,
  "internalNotes": "Nexus Tower Mission Item",
  "abilityNames": [],
  "skillIDs": [],
  "behaviorIDs": [],
  "projectileDamageInfo": {},
  "iconURL": "https://xiphoseer.github.io/lu-res/textures/nexustower/ui/inventory/misc/alien_pet_blue.png",
  "stackSize": 1,
  "price": 0,
  "commendationCost": null,
  "factionTokens": null,
  "levelRequirement": 0
}