{"allItems":[8450],"equipLocationNames":["Right Hand"],"equipLocation":["special_r"],"itemID":8450,"name":"Elite Pickaxe","displayName":"Elite Pickaxe","description":null,"isWeapon":true,"internalNotes":"3/3/3 Smashing","abilityNames":[],"skillIDs":[281],"behaviorIDs":[4715],"meleeDamageInfo":{"damageCombo":"3+3+3","doubleJumpSmash":"2","singleJumpSmash":"3"},"abilityName":"Elite Attack","localeDescription":"Smashes enemies","projectileDamageInfo":{"projectileDamageCombo":"","isChargeUp":false,"chargeUpIsProjectile":false,"isProjectileWeapon":false},"iconURL":"https://xiphoseer.github.io/lu-res/textures/ui/inventory/hands/m3841_199.png","stackSize":1,"price":9000,"commendationCost":null,"factionTokens":null,"levelRequirement":"25"}