{"allItems":[8544],"equipLocationNames":["Headgear"],"equipLocation":["hair"],"itemID":8544,"name":"King's Crown","displayName":"King's Crown","description":null,"isWeapon":false,"internalNotes":"3 AP 4 IP","abilityNames":[],"skillIDs":[362,372],"behaviorIDs":[4244,4254],"abilityName":"Imagination Boost 4","Armor":3,"Imagination":4,"projectileDamageInfo":{"projectileDamageCombo":"","isChargeUp":false,"chargeUpIsProjectile":false,"isProjectileWeapon":false},"iconURL":"https://xiphoseer.github.io/lu-res/textures/ui/inventory/hats/m71015_297.png","stackSize":1,"price":10150,"commendationCost":null,"factionTokens":null,"levelRequirement":"20"}