{"allItems":[14122],"equipLocationNames":["Right Hand"],"equipLocation":["special_r"],"itemID":14122,"name":"Skyme's Blunderbuss","displayName":"Skyme's Blunderbuss","description":"Requires Imagination to fire.","isWeapon":true,"internalNotes":"Community Reward - Tier 4 projectile attack","abilityNames":[],"skillIDs":[1344],"behaviorIDs":[31220],"meleeDamageInfo":{"damageCombo":"1+1+1","chargeUpImaginationCost":3,"doubleJumpSmash":"2","singleJumpSmash":"3"},"abilityName":"Elite Ranged Attack","chargeUpDescription":"Fire a 5 damage projectile","projectileDamageInfo":{"chargeUpDamage":"5","projectileDamageCombo":"3+3+3","isChargeUp":true,"chargeUpIsProjectile":true,"isProjectileWeapon":true},"iconURL":"https://xiphoseer.github.io/lu-res/textures/ui/inventory/hands/m2561_26.png","stackSize":1,"price":15000,"commendationCost":null,"factionTokens":null,"levelRequirement":"27"}