{"allItems":[12876],"equipLocationNames":["tail_a"],"equipLocation":["tail_a"],"itemID":12876,"name":"Test - Do Not Delete - Type 1 - Tail 1","displayName":"","description":"Modular Creature Type 1 Tail 1","isWeapon":false,"internalNotes":null,"abilityNames":[],"skillIDs":[],"behaviorIDs":[],"projectileDamageInfo":{},"iconURL":"https://xiphoseer.github.io/lu-res/textures/ui/inventory/hats/custom_flower_hat.png","stackSize":1,"price":0,"commendationCost":null,"factionTokens":null,"levelRequirement":0}