{
  "allItems": [
    12969
  ],
  "equipLocationNames": [
    "Left Hand"
  ],
  "equipLocation": [
    "special_l"
  ],
  "isPackage": false,
  "itemID": 12969,
  "name": "Knight Shield 3 Color Variant",
  "displayName": "Knight Shield 3",
  "description": "Rank 3 Specialty Kit Item",
  "isWeapon": false,
  "internalNotes": "Rank 3 Specialty Kit Item - Color Variant",
  "abilityNames": [],
  "skillIDs": [
    362,
    369,
    565
  ],
  "behaviorIDs": [
    4244,
    4251,
    8910
  ],
  "abilityName": "Shield Slam 2",
  "Armor": 3,
  "Imagination": 1,
  "localeDescription": "Makes you rush forward, doing 10 damage and knocking down the enemy that you strike",
  "abilityImaginationCost": 7,
  "cooldowngroup": 24,
  "cooldownTime": 7,
  "projectileDamageInfo": {
    "projectileDamageCombo": "",
    "isChargeUp": false,
    "chargeUpIsProjectile": false,
    "isProjectileWeapon": false
  },
  "iconURL": "https://xiphoseer.github.io/lu-res/textures/auramar/ui/inventory/faction%20kits/knight_shield_3_variant.png",
  "stackSize": 1,
  "price": 7500,
  "commendationCost": null,
  "factionTokens": 180,
  "levelRequirement": "30"
}