{
  "allItems": [
    13431
  ],
  "equipLocationNames": [
    null
  ],
  "equipLocation": [
    null
  ],
  "isPackage": false,
  "itemID": 13431,
  "name": "Trophy Behavior",
  "displayName": "Trophy Behavior",
  "description": "A behavior that makes a trophy congratulate and reward the player when the model is touched.",
  "isWeapon": false,
  "internalNotes": "A reward behavior for the Trophy model",
  "abilityNames": [],
  "skillIDs": [],
  "behaviorIDs": [],
  "projectileDamageInfo": {},
  "iconURL": "https://xiphoseer.github.io/lu-res/textures/ui/inventory/models/rew_bvr_trophy.png",
  "stackSize": 0,
  "price": 999,
  "commendationCost": null,
  "factionTokens": null,
  "levelRequirement": 0
}