{"name":"Model Reward Winter Gingerbread House Window 1","displayName":"Winter Gingerbread House Window Model 1","iconURL":"https://xiphoseer.github.io/lu-res/textures/ui/inventory/models/rew_winter_gingerbreadhouse_window01.png","stackSize":10,"price":740,"commendationCost":10,"factionTokens":8,"levelRequirement":0,"itemID":11879,"type":"Loot","isSoldByVendor":true,"vendors":[],"numberOfVendors":0,"commendationVendor":[{"ID":13806,"Name":"Commendation Vendor","DisplayName":"Honor Accolade - Commendation Vendor"}]}