{"objectID":11177,"type":"UserGeneratedNPCs","isMissionGiver":false,"isVendor":true,"soldItems":[{"soldItemID":9450,"soldItemIDName":"CarModule_Wheels_r","soldItemIDDisplayName":"Red Rim Wheels"},{"soldItemID":9451,"soldItemIDName":"CarModule_Wheels_y","soldItemIDDisplayName":"Yellow Rim Wheels"},{"soldItemID":9452,"soldItemIDName":"CarModule_Wheels_w","soldItemIDDisplayName":"White Rim Wheels"},{"soldItemID":9453,"soldItemIDName":"CarModule_Wheels_bk","soldItemIDDisplayName":"Black Rim Wheels"},{"soldItemID":3039,"soldItemIDName":"Green Imaginite","soldItemIDDisplayName":"Green Imaginite"},{"soldItemID":12021,"soldItemIDName":"CarFV1_FrontBumper_r","soldItemIDDisplayName":"Fire Brawl Front Bumper"},{"soldItemID":12023,"soldItemIDName":"CarFV1_FrontPanel_r","soldItemIDDisplayName":"Fire Brawl Engine Panel"},{"soldItemID":12025,"soldItemIDName":"CarFV1_RearBumper_r","soldItemIDDisplayName":"Fire Brawl Rear Bumper"},{"soldItemID":12027,"soldItemIDName":"CarFV1_RearPanel_r","soldItemIDDisplayName":"Fire Brawl Rear Panel"},{"soldItemID":12029,"soldItemIDName":"CarFV1_SidePanels_r","soldItemIDDisplayName":"Fire Brawl Side Panels"},{"soldItemID":12031,"soldItemIDName":"CarFV2_FrontBumper_y","soldItemIDDisplayName":"Mach Lava Front Bumper"},{"soldItemID":12033,"soldItemIDName":"CarFV2_FrontPanel_y","soldItemIDDisplayName":"Mach Lava Engine Panel"},{"soldItemID":12035,"soldItemIDName":"CarFV2_RearBumper_y","soldItemIDDisplayName":"Mach Lava Rear Bumper"},{"soldItemID":12037,"soldItemIDName":"CarFV2_RearPanel_y","soldItemIDDisplayName":"Mach Lava Rear Panel"},{"soldItemID":12039,"soldItemIDName":"CarFV2_SidePanels_y","soldItemIDDisplayName":"Mach Lava Side Panels"},{"soldItemID":7730,"soldItemIDName":"Red Racing Helmet","soldItemIDDisplayName":"Red Racing Helmet"},{"soldItemID":7991,"soldItemIDName":"Black Racing Helmet","soldItemIDDisplayName":"Black Racing Helmet"},{"soldItemID":7992,"soldItemIDName":"Blue Racing Helmet","soldItemIDDisplayName":"Blue Racing Helmet"},{"soldItemID":8037,"soldItemIDName":"Green Racing Helmet","soldItemIDDisplayName":"Green Racing Helmet"},{"soldItemID":8129,"soldItemIDName":"Car Module - Chassis","soldItemIDDisplayName":"Car Chassis"},{"soldItemID":8130,"soldItemIDName":"CarModule_Wheels_gr","soldItemIDDisplayName":"Steel Rim Wheels"}],"name":"FV Race Vendor - Race scene","displayName":"Yam Waterwolf - Racing Vendor","description":"FV Race Vendor - Race","internalNotes":null,"iconURL":"https://xiphoseer.github.io//lu-res/mesh//overhead_indicators//icon_vendor.png"}