{"allItems":[6195],"equipLocationNames":[null],"equipLocation":[null],"itemID":6195,"name":"Test Speed Boost Consumable","displayName":"Manic Motion Potion","description":"Increases your speed for a short time","isWeapon":false,"internalNotes":"test","abilityNames":[],"skillIDs":[181],"behaviorIDs":[1575],"cooldowngroup":0,"cooldownTime":20,"projectileDamageInfo":{"projectileDamageCombo":"","isChargeUp":false,"chargeUpIsProjectile":false,"isProjectileWeapon":false},"iconURL":"https://xiphoseer.github.io/lu-res/textures/ui/inventory/consumables/m330853_24.png","stackSize":10,"price":0,"commendationCost":null,"factionTokens":null,"levelRequirement":0}