{
  "allItems": [
    6198
  ],
  "equipLocationNames": [
    "Headgear"
  ],
  "equipLocation": [
    "hair"
  ],
  "isPackage": false,
  "itemID": 6198,
  "name": "Aviator Helmet",
  "displayName": "Aviator Helmet",
  "description": null,
  "isWeapon": false,
  "internalNotes": "1 IP",
  "abilityNames": [],
  "skillIDs": [
    369
  ],
  "behaviorIDs": [
    4251
  ],
  "abilityName": "Imagination Boost 1",
  "Imagination": 1,
  "projectileDamageInfo": {
    "projectileDamageCombo": "",
    "isChargeUp": false,
    "chargeUpIsProjectile": false,
    "isProjectileWeapon": false
  },
  "iconURL": "https://xiphoseer.github.io/lu-res/textures/ui/inventory/hats/m30171_194.png",
  "stackSize": 1,
  "price": 925,
  "commendationCost": 10,
  "factionTokens": null,
  "levelRequirement": 0
}