{"allItems":[6205],"equipLocationNames":["Right Hand"],"equipLocation":["special_r"],"itemID":6205,"name":"Superior Halberd of Knockback","displayName":"Superior Halberd of Knockback","description":null,"isWeapon":true,"internalNotes":"1/2/3 Smashing + knockback chargeup","abilityNames":[],"skillIDs":[766],"behaviorIDs":[12867],"meleeDamageInfo":{"damageCombo":"2","chargeUpDamage":"3","chargeUpImaginationCost":1,"doubleJumpSmash":"1","singleJumpSmash":"1"},"abilityName":"Superior Attack with Knockback","chargeUpDescription":"Knocks back enemies","projectileDamageInfo":{"chargeUpDamage":"3","projectileDamageCombo":"","isChargeUp":true,"chargeUpIsProjectile":false,"isProjectileWeapon":false},"iconURL":"https://xiphoseer.github.io/lu-res/textures/ui/inventory/hands/m6123_199.png","stackSize":1,"price":5675,"commendationCost":10,"factionTokens":null,"levelRequirement":0}