{
  "allItems": [
    6263
  ],
  "equipLocationNames": [
    "Torso"
  ],
  "equipLocation": [
    "chest"
  ],
  "isPackage": false,
  "itemID": 6263,
  "name": "Pet Doberman Shirt",
  "displayName": "Pet Doberman Shirt",
  "description": null,
  "isWeapon": false,
  "internalNotes": "1 IP",
  "abilityNames": [],
  "skillIDs": [
    369
  ],
  "behaviorIDs": [
    4251
  ],
  "abilityName": "Imagination Boost 1",
  "Imagination": 1,
  "projectileDamageInfo": {
    "projectileDamageCombo": "",
    "isChargeUp": false,
    "chargeUpIsProjectile": false,
    "isProjectileWeapon": false
  },
  "iconURL": "https://xiphoseer.github.io/lu-res/textures/ui/inventory/torsos/pet/m73200_moredog.png",
  "stackSize": 1,
  "price": 5650,
  "commendationCost": null,
  "factionTokens": null,
  "levelRequirement": 0
}