{"id":1687,"rewards":[],"type":"Mission","title":"Darkflame's Denial","giverID":12262,"giverName":"Vanda Darkflame - Paradox Faction Leader","returnToID":12258,"returnToName":"Hael Storm - Venture League Faction Leader","description":"Take that information back to Hael. We have nothing else to share.","objective":"Return to Hael Storm in the Venture League Observatory.","chooseOne":0,"stats":[],"LEGOScore":30,"rewardCoins":250,"isRepeatable":0,"vaultSpace":0,"iconurl":"https://xiphoseer.github.io/lu-res/textures/nexustower/ui/missioncomics/nexustower/task_icons/mission_haelstorm.png"}