{
  "allItems": [
    11462
  ],
  "equipLocationNames": [
    "Left Hand"
  ],
  "equipLocation": [
    "special_l"
  ],
  "isPackage": false,
  "itemID": 11462,
  "name": "Shinobi Offhand 2 - Proxy",
  "displayName": "Shinobi Offhand 2 - Proxy",
  "description": "Rank 2 Specialty Kit Item. Tied to Shinobi Weapon 2",
  "isWeapon": false,
  "internalNotes": "Rank 2 Specialty Kit Item - Proxy",
  "abilityNames": [],
  "skillIDs": [
    1078
  ],
  "behaviorIDs": [
    23759
  ],
  "abilityName": "Shinobi Rush 1",
  "localeDescription": "Makes you rush forward, doing N damage to enemies that you strike",
  "abilityImaginationCost": 6,
  "cooldowngroup": 24,
  "cooldownTime": 8,
  "projectileDamageInfo": {
    "projectileDamageCombo": "",
    "isChargeUp": false,
    "chargeUpIsProjectile": false,
    "isProjectileWeapon": false
  },
  "iconURL": "https://xiphoseer.github.io/lu-res/textures/freetrial/ui/inventory/factionkits/shinobi2_sword.png",
  "stackSize": 1,
  "price": 0,
  "commendationCost": null,
  "factionTokens": 0,
  "levelRequirement": 0
}