{"allItems":[9775],"equipLocationNames":[""],"equipLocation":[""],"itemID":9775,"name":"Basic Tree Model Pack","displayName":"Basic Tree Model Pack","description":"Double-click to open this pack of models!","isWeapon":false,"internalNotes":"5 basic trees","abilityNames":[],"skillIDs":[],"behaviorIDs":[],"projectileDamageInfo":{},"iconURL":"https://xiphoseer.github.io/lu-res/textures/ui/inventory/presents/present_gray.png","stackSize":1,"price":0,"commendationCost":10,"factionTokens":null,"levelRequirement":0}