{
  "allItems": [
    11802
  ],
  "equipLocationNames": [
    "Extra_1"
  ],
  "equipLocation": [
    "Extra_1"
  ],
  "isPackage": false,
  "itemID": 11802,
  "name": "Model Reward Farm Shed Door 1",
  "displayName": "Farm Shed Door Model 1",
  "description": "A model for your property!",
  "isWeapon": false,
  "internalNotes": null,
  "abilityNames": [],
  "skillIDs": [],
  "behaviorIDs": [],
  "projectileDamageInfo": {},
  "iconURL": "https://xiphoseer.github.io/lu-res/textures/ui/inventory/models/rew_shed_door01.png",
  "stackSize": 10,
  "price": 1220,
  "commendationCost": null,
  "factionTokens": null,
  "levelRequirement": 0
}