{"id":329,"rewards":[],"type":"Mission","title":"Trigger Happy","giverID":6224,"giverName":"Bert Scurvyburp - Pirate Quartermaster","returnToID":4853,"returnToName":"Swabbie the Monkey","description":"Yeh gotta stop him 'fore he shoots up the place!","objective":"Talk to the mysterious shooter atop Brig Rock in Gnarled Forest.","chooseOne":0,"stats":[],"LEGOScore":105,"rewardCoins":0,"isRepeatable":0,"vaultSpace":0,"iconurl":"https://xiphoseer.github.io/lu-res/textures/ui/missioncomics/wonderland/gnarled_forest/task_icons/mission_329.png"}