{"id":470,"rewards":[{"name":"Castle Model Pack 6","itemID":9726,"count":1},{"name":"Castle Model Pack 6","itemID":10401,"count":1}],"type":"Mission","title":"Brick Collection","giverID":6010,"giverName":"Fitz Vanderbuilt - Sentinel Faction Engineer","returnToID":6010,"returnToName":"Fitz Vanderbuilt - Sentinel Faction Engineer","description":"Head up to the Monument and get those bricks!","objective":"Smash lumber piles near the Monument to find bricks for the wall at the Sentinel Base Camp.","chooseOne":1,"stats":[],"LEGOScore":15,"rewardCoins":100,"isRepeatable":0,"vaultSpace":0,"iconurl":"https://xiphoseer.github.io/lu-res/textures/ui/missioncomics/wonderland/avant_gardens/task_icons/collectmission_470.png"}