{"allItems":[1272],"equipLocationNames":["Right Hand"],"equipLocation":["special_r"],"itemID":1272,"name":"Test Chargeup Hammer","displayName":null,"description":null,"isWeapon":true,"internalNotes":null,"abilityNames":[],"skillIDs":[146],"behaviorIDs":[12508],"meleeDamageInfo":{"damageCombo":"0","chargeUpImaginationCost":1,"doubleJumpSmash":"1","singleJumpSmash":"1"},"abilityName":"Basic Attack with Stun","chargeUpDescription":"Stuns enemies","projectileDamageInfo":{"chargeUpDamage":"0","projectileDamageCombo":"","isChargeUp":true,"chargeUpIsProjectile":false,"isProjectileWeapon":false},"iconURL":"https://xiphoseer.github.io/lu-res/textures/ui/inventory/hands/m4522_26.png","stackSize":1,"price":0,"commendationCost":null,"factionTokens":null,"levelRequirement":0}